<MesoTS>
<SurvStations num="122">
<station type="2" interval="300" zone="5" segid = "940" id = "5" pos = "0.68">
<sensor id="-5" laneid = "-1"/>
</station>
<station type="2" interval="300" zone="5" segid = "6820" id = "7" pos = "0.49">
<sensor id="-7" laneid = "-1"/>
</station>
<station type="2" interval="300" zone="5" segid = "6900" id = "8" pos = "0.71">
<sensor id="-8" laneid = "-1"/>
</station>
<station type="2" interval="300" zone="5" segid = "7000" id = "10" pos = "0.91">
<sensor id="-10" laneid = "-1"/>
</station>
<station type="2" interval="300" zone="5" segid = "6900" id = "44" pos = "0.81">
<sensor id="-44" laneid = "-1"/>
</station>
<station type="2" interval="300" zone="5" segid = "7000" id = "17" pos = "0.06">
<sensor id="-17" laneid = "-1"/>
</station>
<station type="1" interval="300" zone="5" segid = "940" id = "-9" pos = "0.1">
<sensor id="7" laneid = "9401"/>
<sensor id="8" laneid = "9402"/>
<sensor id="9" laneid = "9403"/>
</station>
<station type="1" interval="300" zone="5" segid = "9090" id = "-10" pos = "1.00">
<sensor id="10" laneid = "90901"/>
</station>
<station type="1" interval="300" zone="5" segid = "9200" id = "-14" pos = "0.17">
<sensor id="12" laneid = "92001"/>
</station>
<station type="1" interval="300" zone="5" segid = "7000" id = "-15" pos = "0.18">
<sensor id="13" laneid = "70001"/>
<sensor id="14" laneid = "70002"/>
<sensor id="15" laneid = "70003"/>
</station>
</SurvStations>
</MesoTS>
